Metadata-Version: 1.0
Name: passwordmanpro-cli
Version: 0.2.1
Summary: Python based command line interface for Password Manager Pro
Home-page: https://github.com/rmetcalf9/passwordmanpro_cli
Author: Robert Metcalf
Author-email: rmetcalf9@googlemail.com
License: MIT
Platform: UNKNOWN
